Metadata-Version: 2.1
Name: dimdim-cli
Version: 0.0.2
Summary: DimDim Backend team CLI.
Home-page: https://dimdim.com.ua/dimdim-cli/
Author: Serhii Berebko
Author-email: s.berebko@wrenchtech.io
License: BSD-3-Clause License
Keywords: dimdim gitlab styleguide
Platform: UNKNOWN
Classifier: License :: OSI Approved :: BSD License
Classifier: Topic :: Software Development :: Build Tools
Classifier: Programming Language :: Python
Classifier: Programming Language :: Python :: Implementation :: CPython
Requires-Python: >=3.5.2
